{
  "project_info": {
    "project_number": "375221724339",
    "project_id": "facturacionreparacioncelulares",
    "storage_bucket": "facturacionreparacioncelulares.appspot.com"
  },
  "client": [
    {
      "client_info": {
        "mobilesdk_app_id": "1:375221724339:android:d7790ff1ac50aca142fcc6",
        "android_client_info": {
          "package_name": "com.example.factureroreparacioncelular"
        }
      },
      "oauth_client": [],
      "api_key": [
        {
          "current_key": "AIzaSyDDyE2J-r7b5f3Zbk1urZZuKxtDRrZmbxY"
        }
      ],
      "services": {
        "appinvite_service": {
          "other_platform_oauth_client": []
        }
      }
    }
  ],
  "configuration_version": "1"
}